oscarbluelight/__init__.py
oscarbluelight/basket_utils.py
oscarbluelight/caching.py
oscarbluelight/defaults.py
oscarbluelight/mixins.py
oscarbluelight/py.typed
oscarbluelight/tasks.py
oscarbluelight/dashboard/__init__.py
oscarbluelight/dashboard/offers/__init__.py
oscarbluelight/dashboard/offers/api_views.py
oscarbluelight/dashboard/offers/apps.py
oscarbluelight/dashboard/offers/forms.py
oscarbluelight/dashboard/offers/models.py
oscarbluelight/dashboard/offers/reports.py
oscarbluelight/dashboard/offers/serializers.py
oscarbluelight/dashboard/offers/views.py
oscarbluelight/dashboard/ranges/__init__.py
oscarbluelight/dashboard/ranges/apps.py
oscarbluelight/dashboard/ranges/forms.py
oscarbluelight/dashboard/ranges/models.py
oscarbluelight/dashboard/ranges/views.py
oscarbluelight/dashboard/vouchers/__init__.py
oscarbluelight/dashboard/vouchers/apps.py
oscarbluelight/dashboard/vouchers/forms.py
oscarbluelight/dashboard/vouchers/views.py
oscarbluelight/locale/es/LC_MESSAGES/django.po
oscarbluelight/locale/es/LC_MESSAGES/djangojs.po
oscarbluelight/offer/__init__.py
oscarbluelight/offer/admin.py
oscarbluelight/offer/applicator.py
oscarbluelight/offer/apps.py
oscarbluelight/offer/benefits.py
oscarbluelight/offer/conditions.py
oscarbluelight/offer/constants.py
oscarbluelight/offer/groups.py
oscarbluelight/offer/handlers.py
oscarbluelight/offer/line_filters.py
oscarbluelight/offer/models.py
oscarbluelight/offer/reports.py
oscarbluelight/offer/results.py
oscarbluelight/offer/signals.py
oscarbluelight/offer/sql.py
oscarbluelight/offer/tasks.py
oscarbluelight/offer/types.py
oscarbluelight/offer/upsells.py
oscarbluelight/offer/utils.py
oscarbluelight/offer/migrations/0001_initial.py
oscarbluelight/offer/migrations/0002_auto_20151210_1053.py
oscarbluelight/offer/migrations/0002_compoundcondition.py
oscarbluelight/offer/migrations/0003_merge.py
oscarbluelight/offer/migrations/0004_conditionaloffer_groups.py
oscarbluelight/offer/migrations/0005_auto_20160719_1238.py
django_oscar_bluelight-5.12.0.dist-info/METADATA
django_oscar_bluelight-5.12.0.dist-info/WHEEL
django_oscar_bluelight-5.12.0.dist-info/licenses/LICENSE
django_oscar_bluelight-5.12.0.dist-info/RECORD
