Metadata-Version: 2.4
Name: django-oscar-bluelight
Version: 5.12.0
Summary: Bluelight Specials - Enhancements to the offer and vouchers features for Django Oscar.
Project-URL: Homepage, https://gitlab.com/thelabnyc/django-oscar/django-oscar-bluelight
Project-URL: Repository, https://gitlab.com/thelabnyc/django-oscar/django-oscar-bluelight
Author-email: thelab <thelabdev@thelab.co>
License: ISC
License-File: LICENSE
Requires-Python: >=3.13
Requires-Dist: django-oscar<4.2,>=4.0
Requires-Dist: django>=5.2
Requires-Dist: djangorestframework<4,>=3.16.1
Requires-Dist: thelabdb>=0.6.1
Provides-Extra: celery
Requires-Dist: celery>=5.6.2; extra == 'celery'
Provides-Extra: django-tasks
Requires-Dist: django-tasks<0.11.1,>=0.11.0; extra == 'django-tasks'
